shtestlib/__init__.py
shtestlib/shtestlib.py
shtestlib/__init__.py
shtestlib/shtestlib.py
shtestlib-0.1.0.dist-info/METADATA
shtestlib-0.1.0.dist-info/WHEEL
shtestlib-0.1.0.dist-info/top_level.txt
shtestlib-0.1.0.dist-info/RECORD
