Metadata-Version: 2.1
Name: shtestlib
Version: 0.1.0
Summary: A simple custom library
Home-page: https://www.hyundaifuturenet.com/
Author: hd-ai-lab
Author-email: store_admin@hyundaifuturenet.co.kr
Classifier: Programming Language :: Python :: 3
Classifier: License :: OSI Approved :: MIT License
Classifier: Operating System :: OS Independent
Requires-Python: >=3.6
Requires-Dist: requests
